File_menu.png
Help_menu.png
MANIFEST.in
README.md
list_files.png
main_window.png
messagebox.png
multicomplex.py
multifunctions.py
options.png
selection_folder.png
setup.py
example1/.DS_Store
example1/A_B.pdb
example1/A_C.pdb
example1/A_D.pdb
example1/B_C.pdb
example1/B_D.pdb
example1/B_E.pdb
example1/C_D.pdb
example1/C_E.pdb 
example1/C_F.pdb
example1/D_E.pdb
example1/D_F.pdb
example1/D_G.pdb
example1/E_F.pdb
example1/E_G.pdb
example1/E_H.pdb
example1/F_A.pdb
example1/F_G.pdb
example1/F_H.pdb
example2/PAIR_AB.pdb
example2/PAIR_AC.pdb
example2/PAIR_AD.pdb
example2/PAIR_AF.pdb
example2/PAIR_BA.pdb
example2/PAIR_BE.pdb
example2/PAIR_BF.pdb
example2/PAIR_CA.pdb
example2/PAIR_CB.pdb
example2/PAIR_CD.pdb
example2/PAIR_CJ.pdb
example2/PAIR_DA.pdb
example2/PAIR_DB.pdb
example2/PAIR_DC.pdb
example2/PAIR_DI.pdb
example2/PAIR_EF.pdb
example2/PAIR_EL.pdb
example2/PAIR_FA.pdb
example2/PAIR_FE.pdb
example2/PAIR_FK.pdb
example2/PAIR_GI.pdb
example2/PAIR_GJ.pdb
example2/PAIR_HG.pdb
example2/PAIR_HI.pdb
example2/PAIR_ID.pdb
example2/PAIR_IH.pdb
example2/PAIR_JC.pdb
example2/PAIR_JG.pdb
example2/PAIR_JI.pdb
example2/PAIR_KE.pdb
example2/PAIR_KH.pdb
example2/PAIR_LE.pdb
example2/PAIR_LG.pdb
example2/PAIR_LK.pdb
example3/.DS_Store
example3/OP.pdb
example3/OR.pdb
example3/PQ.pdb
example3/PR.pdb
example3/QR.pdb
example3/QS.pdb
example3/RS.pdb
example3/RT.pdb
example3/ST.pdb
example3/SU.pdb
example3/TU.pdb
example3/TV.pdb
example3/UV.pdb
example3/UW.pdb
example3/VW.pdb
example3/VX.pdb
example3/WX.pdb
example3/WY.pdb
example3/X1.pdb
example3/XY.pdb
example3/Y1.pdb
example3/Y2.pdb
example3/Z1.pdb
example3/Z2.pdb
protcomp.egg-info/PKG-INFO
protcomp.egg-info/SOURCES.txt
protcomp.egg-info/dependency_links.txt
protcomp.egg-info/entry_points.txt
protcomp.egg-info/requires.txt
protcomp.egg-info/top_level.txt