Metadata-Version: 1.0
Name: protcomp
Version: 2.0
Summary: Python package to reconstruct protein complexes from protein pairwise interactions.
Home-page: https://github.com/massonix/Python-project
Author: Ramon Massoni, Winona Oliveros
Author-email: winn95@gmail.com
License: UNKNOWN
Platform: UNKNOWN
